scagnostics.cpython-38-i386-linux-gnu.so
pyscagnostics-0.1.0a4.dist-info/RECORD
pyscagnostics-0.1.0a4.dist-info/WHEEL
pyscagnostics-0.1.0a4.dist-info/METADATA
pyscagnostics-0.1.0a4.dist-info/LICENSE.md
pyscagnostics-0.1.0a4.dist-info/top_level.txt
pyscagnostics/__init__.py
pyscagnostics/scagnostics.cpp
