Metadata-Version: 2.1
Name: pyscagnostics
Version: 0.1.0a4
Summary: Graph theoretic scatterplot diagnostics
Home-page: https://github.com/haishiro/pyscagnostics
License: GPL
Keywords: data analysis scatterplot diagnostics
Platform: UNKNOWN
Classifier: Development Status :: 3 - Alpha
Classifier: License :: OSI Approved :: GNU General Public License (GPL)
Classifier: Topic :: Scientific/Engineering :: Information Analysis
Classifier: Programming Language :: Python
Classifier: Programming Language :: Python :: 3
Classifier: Programming Language :: Python :: 3.6
Classifier: Programming Language :: Python :: 3.7
Classifier: Programming Language :: Python :: 3.8
Classifier: Programming Language :: Python :: Implementation :: CPython
Classifier: Programming Language :: Python :: Implementation :: PyPy
Requires-Python: >=3.6.0
Requires-Dist: numpy (>=1.18.1)
